{"name":"Verify application is Launched and initial screen is loaded properly","id":"gurukula-application-accessibility;verify-application-is-launched-and-initial-screen-is-loaded-properly","testSteps":[{"number":1,"description":"Given Gurukula Application is Launched","duration":8117,"startTime":"2018-10-01T22:53:55.138+02:00[Europe/Paris]","screenshots":[{"screenshot":"5c9e2591e801a57559f8487bb06aa815196e04be28a52e0ef40bb76a70bde084.png"}],"result":"SUCCESS","precondition":false,"children":[{"number":2,"description":"Launch","duration":7423,"startTime":"2018-10-01T22:53:55.557+02:00[Europe/Paris]","screenshots":[{"screenshot":"972764835faf8c5470c063d4cdd75dfc8d242b334dcdeba00dc2110a89345c2b.png"}],"result":"SUCCESS","precondition":false}]},{"number":3,"description":"When Initial home Page is accessible","duration":620,"startTime":"2018-10-01T22:54:03.255+02:00[Europe/Paris]","screenshots":[{"screenshot":"5c9e2591e801a57559f8487bb06aa815196e04be28a52e0ef40bb76a70bde084.png"}],"result":"SUCCESS","precondition":false,"children":[{"number":4,"description":"Verify application is launched","duration":350,"startTime":"2018-10-01T22:54:03.255+02:00[Europe/Paris]","screenshots":[{"screenshot":"5c9e2591e801a57559f8487bb06aa815196e04be28a52e0ef40bb76a70bde084.png"}],"result":"SUCCESS","precondition":false}]},{"number":5,"description":"Then Verify login option is available","duration":561,"startTime":"2018-10-01T22:54:03.875+02:00[Europe/Paris]","screenshots":[{"screenshot":"5c9e2591e801a57559f8487bb06aa815196e04be28a52e0ef40bb76a70bde084.png"}],"result":"SUCCESS","precondition":false,"children":[{"number":6,"description":"Is login link displayed","duration":301,"startTime":"2018-10-01T22:54:03.875+02:00[Europe/Paris]","screenshots":[{"screenshot":"5c9e2591e801a57559f8487bb06aa815196e04be28a52e0ef40bb76a70bde084.png"}],"result":"SUCCESS","precondition":false}]},{"number":7,"description":"And Verify Registration option is available","duration":583,"startTime":"2018-10-01T22:54:04.436+02:00[Europe/Paris]","screenshots":[{"screenshot":"5c9e2591e801a57559f8487bb06aa815196e04be28a52e0ef40bb76a70bde084.png"}],"result":"SUCCESS","precondition":false,"children":[{"number":8,"description":"Is registration link displayed","duration":332,"startTime":"2018-10-01T22:54:04.436+02:00[Europe/Paris]","screenshots":[{"screenshot":"5c9e2591e801a57559f8487bb06aa815196e04be28a52e0ef40bb76a70bde084.png"}],"result":"SUCCESS","precondition":false}]}],"userStory":{"id":"gurukula-application-accessibility","storyName":"Gurukula Application accessibility","path":"src/test/resources/features/accessibility/applicationVerification/ApplicationStatus.feature","narrative":"  In this feature application initial status is verified","type":"feature"},"featureTag":{"name":"Application verification/Gurukula Application accessibility","type":"feature"},"title":"Verify application is Launched and initial screen is loaded properly","tags":[{"name":"VerifyApplicationIsLaunchedAndValidate","type":"tag"},{"name":"Accessibility","type":"theme"},{"name":"UI","type":"tag"},{"name":"Accessibility/Application verification","type":"capability"},{"name":"Application verification/Gurukula application accessibility","type":"feature"}],"startTime":"2018-10-01T22:53:54.665+02:00[Europe/Paris]","duration":10386,"projectKey":"","sessionId":"abb0f95302b822e50eb2522d3826e204","driver":"chrome","manual":false,"testSource":"Cucumber","result":"SUCCESS"}